ura_agi/__init__.py
ura_agi/agi.py
ura_agi/entities.py
ura_agi-0.0.3.dist-info/LICENSE
ura_agi-0.0.3.dist-info/METADATA
ura_agi-0.0.3.dist-info/WHEEL
ura_agi-0.0.3.dist-info/top_level.txt
ura_agi-0.0.3.dist-info/RECORD
