Metadata-Version: 2.1
Name: ura-agi
Version: 0.0.3
Summary: Lib for scripts AGI (Asterisk Gateway Interface)
Home-page: UNKNOWN
Author: Tatianno Alves
Author-email: tferreiraalves@gmail.com
License: MIT License
Keywords: asterisk agi ura query API
Platform: UNKNOWN
Requires-Dist: pyst2
Requires-Dist: wheel
